tash/__init__.py
tash/__main__.py
tash-0.1.0.dist-info/METADATA
tash-0.1.0.dist-info/WHEEL
tash-0.1.0.dist-info/entry_points.txt
tash-0.1.0.dist-info/RECORD
