Metadata-Version: 2.3
Name: tash
Version: 0.1.0
Summary: Educational Platform that runs on the terminal.
Author-email: Ramon Perez <ramonpzg@protonmail.com>
Requires-Python: >=3.8
